manim_main_function/logger.py
manim_main_function/mmf.py
manim_main_function-0.1.2.dist-info/LICENSE
manim_main_function-0.1.2.dist-info/METADATA
manim_main_function-0.1.2.dist-info/WHEEL
manim_main_function-0.1.2.dist-info/RECORD
