Metadata-Version: 2.3
Name: manim-main-function
Version: 0.1.2
Summary: A manim plugin that enables rendering manim scenes using the python main function.
License: MIT
Author: Alexander Nasuta
Author-email: alexander.nasuta@wzl-iqs.rwth-aachen.de
Requires-Python: >=3.11,<4.0
Classifier: License :: OSI Approved :: MIT License
Classifier: Programming Language :: Python :: 3
Classifier: Programming Language :: Python :: 3.11
Classifier: Programming Language :: Python :: 3.12
Classifier: Programming Language :: Python :: 3.13
Requires-Dist: manim (>=0.19.0,<0.20.0)
Requires-Dist: rich (>=14.0.0,<15.0.0)
